{
  "isbn": "9791128214011",
  "title": "우리 눈은 착각쟁이",
  "pages": [
    {
      "page": 9,
      "text": "우리 눈은 착각쟁이야. 아래에 있는 물고기가 더 길어 보이지? 아니야, 두 물고기의 길이는 똑같아. 화살표 모양 때문에 달라 보이는 거야."
    },
    {
      "page": 11,
      "text": "피에로가 몸집이 작은 순서대로 서 있을까? 아니야, 피에로의 몸집은 모두 똑같아. 터널 모양 때문에 달라 보이는 거야."
    },
    {
      "page": 13,
      "text": "선은 삐딱하고, 동그라미는 찌그러졌지? 아니야, 반듯반듯한 선에 동그란 원이야. 빗금 모양 때문에 달라 보이는 거야."
    },
    {
      "page": 18,
      "text": "무엇을 그린 걸까? 요렇게 보면 오리, 조렇게 보면 토끼야. 무늬와 색도 눈을 착각쟁이로 만들어. 실제보다 더 뚱뚱하게 보이게 하고, 더 날씬하게 보이게도 해."
    },
    {
      "page": 29,
      "text": "빙글빙글 뱅글뱅글. 그림이 춤을 추는 것 같아. 우리 눈을 착각쟁이로 만드는 걸 찾아봐. 주위에 얼마든지 있으니까."
    },
    {
      "page": 29,
      "text": "어두운색은 작아 보이게 하고 밝은색은 커 보이게 해. 착시를 이용하면 재미있는 사진도 찍을 수 있어. 글자들은 어떨까? 글자들도 나란히 나란히 모아 놓으면. 출렁출렁 파도처럼 글자들이 춤을 추는 것 같아."
    }
  ]
}