{
  "isbn": "9791165952082",
  "title": "보송보송 얼음 산",
  "pages": [
    {
      "page": 5,
      "text": "“하나야, 할머니 집에 아주 멋진 게 있대.” “정말요? 할머니 집에 갈래요.” “할머니, 할머니, 이게 뭐예요?” “그걸로 빙수를 만들 수 있단다.” "
    },
    {
      "page": 7,
      "text": "얼음을 끼운 다음, 빙글빙글 돌려요. “우아, 보송보송 얼음 산이다!” 빙글빙글 돌리면, 보송보송 얼음 산이 쑥쑥! 빙글빙글 더 돌리면, 보송보송 얼음 산이 쑤욱 쑤욱! "
    },
    {
      "page": 8,
      "text": "“야옹! 하나야, 뭐 하냥?” “아, 까망이구나! 보송보송 얼음 산에 올라가고 있어. 너도 갈래?” “까망아, 얼음 한번 먹어 봐. 어때?” "
    },
    {
      "page": 10,
      "text": "“야옹! 차갑다냥!” 까망이가 부르르! “진짜진짜 차갑지?” 하나도 부르르! “우리 얼음 산을 예쁘게 꾸미자.” 말랑말랑 젤리를 톡톡! 알록달록 과일을 톡톡! "
    },
    {
      "page": 12,
      "text": "“하나야, 나처럼 미끄럼 타라옹. 야옹! 정말 재밌다냥.” “응, 나도 미끄럼 탈래.\" 엉덩이가 너무 차가워. "
    },
    {
      "page": 12,
      "text": "아하! 바나나 썰매를 타자. “우리도 썰매 타고 싶어.” “어? 북극곰과 펭귄이네. 좋아, 너희도 타.” "
    },
    {
      "page": 15,
      "text": "“바나나 썰매, 정말 재밌다!” 한 번, 두 번, 세 번. 주르르! 주르르! 흔들흔들 출렁출렁! “어? 큰일이야! 얼음 산이 무너지려고 해.” 바로 그때. “하나야, 빙수 다 만들었니?” “네! 할머니, 제가 만든 빙수 예쁘죠? 우리 함께 먹어요.” "
    }
  ]
}