{
  "isbn": "9791165431716",
  "title": "아가는 안 먹는대",
  "pages": [
    {
      "page": 1,
      "text": "당근 넣고, 시금치 넣고, 달걀 넣고, 조물조물 만든 주먹밥! 아빠가 아가 먹으라고 만든 아가 밥. “아가야, 밥 먹자!”"
    },
    {
      "page": 3,
      "text": "“싫어, 싫어. 먹기 싫어!” “그럼 강아지야, 밥 먹자. 아가는 안 먹는대.” 강아지가 주먹밥을 우걱우걱 쩝쩝, 뚝딱!"
    },
    {
      "page": 5,
      "text": "“싫어, 싫어. 먹기 싫어!” 고양이가 주먹밥을 할짝할짝 날름날름, 뚝딱! “싫어, 싫어. 먹기 싫어!” “그럼 아가 밥, 아빠가 먹어야지.” 아빠가 주먹밥을 냠냠 쩝쩝, 꿀꺽!"
    },
    {
      "page": 8,
      "text": "아가는 자꾸만 흘끔흘끔. 아가 얼굴이 붉으락푸르락. “강아지랑 고양이, 미워! 아빠도 미워!” “우리 아가 밥, 여기 또 있네.” 아가는 주먹밥을 오물오물 냠냠, 꿀꺽! “우아, 맛있다.”"
    }
  ]
}