{
  "title": "아기 곰의 물고기 인형",
  "author": "임용재",
  "illustrator": "이주은",
  "isbn": "9788994730257",
  "readAge": "유아",
  "publishedYear": 2010,
  "publisher": "인북",
  "classification": "자연탐구",
  "paragraphInfoCount": 28,
  "paragraphInfo": [
    {
      "srcTextID": "18820",
      "srcText": "\"이건 한 뼘도 안 되네. 놓아주어야지.\" \"이건 세 뼘이야. 너무 커. 놓아주자.\" \"딱 두 뼘이구나. 이 물고기들은 엄마에게 갖다 드려야지.\"",
      "srcPage": 13,
      "srcSentenceEA": 7,
      "srcWordEA": 24,
      "queAnsPairInfo": [],
      "queAnsPairInfoCount": 0
    },
    {
      "srcTextID": "18821",
      "srcText": "아기 곰은 강물에 낚싯대를 드리우고 물고기를 잡기 시작했어요. 엄마에게 선물 받을 커다란 물고기 인형을 생각하니 물고기 잡는 게 즐거웠어요. 아기 곰은 잡은 물고기의 길이를 쟀어요.",
      "srcPage": 13,
      "srcSentenceEA": 3,
      "srcWordEA": 27,
      "queAnsPairInfo": [],
      "queAnsPairInfoCount": 0
    },
    {
      "srcTextID": "18831",
      "srcText": "임의 단위. 표준 측정 도구가 아닌 몸이나 물건을 이용하여 측정하는 임의 단위는 도형 학습의 가장 기초가 되는 개념이에요. 길이를 알아보려고 할 때 우리는 일반적으로 자를 사용해요. 자와 같이 통일된 측정 도구의 단위, 즉 cm(센티미터), m(미터), km(킬로미터) 등을 표준 단위라고 하지요.",
      "srcPage": 18,
      "srcSentenceEA": 4,
      "srcWordEA": 43,
      "queAnsPairInfo": [],
      "queAnsPairInfoCount": 0
    },
    {
      "srcTextID": "18832",
      "srcText": "표준 단위를 사용하도록 하기 전에 임의 단위를 먼저 알아보는 것은 다양한 방법으로 크기를 잴 수 있다는 것을 알려 주기 위해서예요. 이 과정에서 아이들은 임의 단위의 부정확함과 불편함까지 이해하고 표준 단위의 필요성을 스스로 깨달을 수 있어요. 아이들이 생활 속에서 다양한 임의 단위를 이용하여 길이나 크기, 양 등을 재어 볼 수 있도록 하세요. 아이들은 보다 쉽게 임의 단위의 개념을 이해하고 나아가 표준 단위 학습에 흥미를 가질 수 있을 거예요.",
      "srcPage": 18,
      "srcSentenceEA": 4,
      "srcWordEA": 70,
      "queAnsPairInfo": [],
      "queAnsPairInfoCount": 0
    },
    {
      "srcTextID": "18812",
      "srcText": "\"이 나무는 한 아름보다 크구나.\" \"이 나무는 한 아름보다 작네.\" \"앗! 딱 한 아름이다!\" 아기 곰은 한 아름 둘레의 나무 열 그루를 찾았어요.",
      "srcPage": 9,
      "srcSentenceEA": 4,
      "srcWordEA": 25,
      "queAnsPairInfo": [],
      "queAnsPairInfoCount": 0
    },
    {
      "srcTextID": "18813",
      "srcText": "언덕을 넘으니 엄마 곰이 말한 숲이 나왔어요. \"먼저 둘레가 한 아름인 나무를 찾아야지.\" 아기 곰은 팔을 쭉 벌려 나무 둘레를 쟀어요.",
      "srcPage": 9,
      "srcSentenceEA": 3,
      "srcWordEA": 22,
      "queAnsPairInfo": [],
      "queAnsPairInfoCount": 0
    },
    {
      "srcTextID": "18808",
      "srcText": "\"엄마는 무슨 선물을 받고 싶으세요?\" \"엄마는 네가 직접 잡은 물고기를 맛있게 구워 먹고 싶구나.\" \"알았어요, 엄마. 제가 가서 물고기를 잡아 올게요.\"",
      "srcPage": 7,
      "srcSentenceEA": 4,
      "srcWordEA": 22,
      "queAnsPairInfo": [],
      "queAnsPairInfoCount": 0
    },
    {
      "srcTextID": "18809",
      "srcText": "아기 곰의 말에 엄마 곰은 빙긋 웃었어요. 아기 곰은 물고기를 잡으러 갈 준비를 마쳤어요. \"엄마, 강까지 가는 길을 알려 주세요.\"",
      "srcPage": 7,
      "srcSentenceEA": 3,
      "srcWordEA": 21,
      "queAnsPairInfo": [],
      "queAnsPairInfoCount": 0
    },
    {
      "srcTextID": "18814",
      "srcText": "\"이 나뭇잎은 한 뼘이 안 돼.\" \"와, 딱 한 뼘이다!\" 한 아름 둘레의 나무 열 그루 가운데 한 뼘 길이의 나뭇잎을 가진 것은 세 그루였어요. 아기 곰은 세 그루의 나무를 콩콩 두드렸어요. 그러자 나무 뒤로 세 개의 무지개 다리가 생겼어요.",
      "srcPage": 10,
      "srcSentenceEA": 5,
      "srcWordEA": 43,
      "queAnsPairInfo": [],
      "queAnsPairInfoCount": 0
    },
    {
      "srcTextID": "18815",
      "srcText": "이제 한 뼘 크기의 나뭇잎을 찾아야 해요. 아기 곰은 손가락을 쭉 펴서 나뭇잎 길이를 쟀어요. \"이 나뭇잎은 한 뼘이 넘네.\"",
      "srcPage": 10,
      "srcSentenceEA": 3,
      "srcWordEA": 21,
      "queAnsPairInfo": [],
      "queAnsPairInfoCount": 0
    },
    {
      "srcTextID": "18828",
      "srcText": "김 100장은 한 톳. 굴비 20마리는 한 두름. 손을 이용하여 세는 단위. 한 자밤. 한 줌. 한 움큼.",
      "srcPage": 17,
      "srcSentenceEA": 6,
      "srcWordEA": 23,
      "queAnsPairInfo": [],
      "queAnsPairInfoCount": 0
    },
    {
      "srcTextID": "18829",
      "srcText": "옛날부터 물건을 셀 때 쓰던 단위. 뭉쳐 놓은 실은 한 타래. 막대에 감아 놓은 실은 한 꾸리. 둥글게 감아 놓은 실은 한 토리.",
      "srcPage": 17,
      "srcSentenceEA": 4,
      "srcWordEA": 26,
      "queAnsPairInfo": [],
      "queAnsPairInfoCount": 0
    },
    {
      "srcTextID": "18830",
      "srcText": "이런저런 단위들. 아기 곰이 자기 방 벽에 그림을 잔뜩 붙여 놓았어요. 그림을 살펴보면서 옛날부터 사용되던 단위와 다양한 측정 방법에 대해 알아보아요.",
      "srcPage": 17,
      "srcSentenceEA": 3,
      "srcWordEA": 23,
      "queAnsPairInfo": [],
      "queAnsPairInfoCount": 0
    },
    {
      "srcTextID": "18825",
      "srcText": "하지만 엄마 곰은 약속대로 아기 곰에게 직접 만든 물고기 인형을 선물해 주었어요. \"엄지손가락만 한 동그란 눈과 한 뼘만 한 입과 한 아름 둘레의 몸통과 세 걸음 길이의 물고기 인형이란다.\" 아기 곰은 깜짝 놀랐어요. 물고기 인형이 자기 몸집보다 훨씬 컸기 때문이에요. 어떻게 된 일일까요?",
      "srcPage": 15,
      "srcSentenceEA": 5,
      "srcWordEA": 46,
      "queAnsPairInfo": [],
      "queAnsPairInfoCount": 0
    },
    {
      "srcTextID": "18826",
      "srcText": "\"누나 곰은 한 아름. 아빠 곰은 세 아름도 넘네.\" \"내 손이 너무 작아서 뼘으로 나무의 키를 재기는 힘들겠어.\" \"키를 이용하면 한길, 두길, 세길, 네길!\"",
      "srcPage": 16,
      "srcSentenceEA": 4,
      "srcWordEA": 25,
      "queAnsPairInfo": [],
      "queAnsPairInfoCount": 0
    },
    {
      "srcTextID": "18827",
      "srcText": "자가 된 아기 곰. 귀여운 아기 곰이 몸을 이용해서 길이를 재고 있어요. 몸을 이용한 다양한 임의 단위를 알아보고 아기 곰을 따라 길이를 재어 보세요. \"두 팔을 쭉 펴서 한 발, 두 발, 세 발, 네 발!\"",
      "srcPage": 16,
      "srcSentenceEA": 4,
      "srcWordEA": 38,
      "queAnsPairInfo": [],
      "queAnsPairInfoCount": 0
    },
    {
      "srcTextID": "18818",
      "srcText": "\"이상하다. 세 개의 무지개 다리는 모두 다섯 걸음이었는데.\" 아기 곰은 고개를 갸우뚱했어요. 나는 왜 그런지 알지!",
      "srcPage": 12,
      "srcSentenceEA": 3,
      "srcWordEA": 19,
      "queAnsPairInfo": [],
      "queAnsPairInfoCount": 0
    },
    {
      "srcTextID": "18819",
      "srcText": "아기 곰은 보통 걸음으로 세 번째 다리를 건넜어요. \"하나, 둘, 셋, 넷, 다섯.\" 드디어 아기 곰은 은빛 물고기가 가득한 푸른 강에 다다랐어요.",
      "srcPage": 12,
      "srcSentenceEA": 3,
      "srcWordEA": 23,
      "queAnsPairInfo": [],
      "queAnsPairInfoCount": 0
    },
    {
      "srcTextID": "18816",
      "srcText": "아기 곰은 두 번째 다리를 작은 걸음으로 건넜어요. \"하나, 둘, 셋, 넷, 다섯.\" 그런데 이번에는 흙탕물이 나타났어요. \"여긴 물고기가 없잖아.\" 아기 곰은 실망하여 되돌아갔어요. 이번엔 너무 작은 걸음이야.",
      "srcPage": 11,
      "srcSentenceEA": 6,
      "srcWordEA": 31,
      "queAnsPairInfo": [],
      "queAnsPairInfoCount": 0
    },
    {
      "srcTextID": "18817",
      "srcText": "아기 곰은 첫 번째 다리를 큰 걸음으로 건너며 숫자를 세었어요. \"하나, 둘, 셋, 넷, 다섯.\" 그런데 눈앞에 고래가 사는 바다가 펼쳐졌어요. \"여기가 아니네.\" 아기 곰은 얼른 되돌아갔어요. 너무 큰 걸음이잖아.",
      "srcPage": 11,
      "srcSentenceEA": 6,
      "srcWordEA": 33,
      "queAnsPairInfo": [],
      "queAnsPairInfoCount": 0
    },
    {
      "srcTextID": "18807",
      "srcText": "그날 저녁, 엄마 곰이 아기 곰에게 말했어요. \"엄마랑 서로 선물을 주고받으면 어떨까?\" \"좋아요, 엄마!\" 아기 곰이 신이 나서 대답했어요. \"눈은 엄지손가락만 하고, 입은 한 뼘, 몸통은 한 아름 둘레, 키는 세 걸음 길이의 커다란 물고기 인형을 갖고 싶어요.\"",
      "srcPage": 6,
      "srcSentenceEA": 5,
      "srcWordEA": 39,
      "queAnsPairInfo": [],
      "queAnsPairInfoCount": 0
    },
    {
      "srcTextID": "18810",
      "srcText": "\"저기 보이는 언덕을 넘으면 숲이 나올 거야. 그곳에서 둘레가 한 아름이고, 나뭇잎 길이가 한 뼘인 나무를 찾으렴. 그 나무를 두드리면 예쁜 무지개 다리가 생기는데, 다섯 걸음 길이의 다리를 건너야만 강이 나온단다.\"",
      "srcPage": 8,
      "srcSentenceEA": 3,
      "srcWordEA": 33,
      "queAnsPairInfo": [],
      "queAnsPairInfoCount": 0
    },
    {
      "srcTextID": "18811",
      "srcText": "\"참, 꼭 두 뼘 길이의 물고기를 잡아 와야 한다.\" \"네, 엄마. 다녀오겠습니다!\" 아기 곰은 손을 흔들며 집을 나섰어요. 아기 곰을 보내고 집으로 들어온 엄마 곰은 커다란 물고기 인형을 만들기 시작했어요.",
      "srcPage": 8,
      "srcSentenceEA": 5,
      "srcWordEA": 33,
      "queAnsPairInfo": [],
      "queAnsPairInfoCount": 0
    },
    {
      "srcTextID": "18822",
      "srcText": "\"정말 기특하구나! 두 뼘인지 어디 볼까?\" 엄마 곰은 손가락을 펴서 물고기 길이를 재어 보았어요. \"얘야, 두 뼘이 안 되는데?\"",
      "srcPage": 14,
      "srcSentenceEA": 4,
      "srcWordEA": 21,
      "queAnsPairInfo": [],
      "queAnsPairInfoCount": 0
    },
    {
      "srcTextID": "18823",
      "srcText": "엄마 손으로 재니 정말 두 뼘이 되지 않았어요. \"이상하다. 오는 도중에 물고기가 줄었나 봐요.\" 아기 곰은 울상이 되었어요. 엄마 곰 손이 더 크잖아.",
      "srcPage": 14,
      "srcSentenceEA": 4,
      "srcWordEA": 26,
      "queAnsPairInfo": [],
      "queAnsPairInfoCount": 0
    },
    {
      "srcTextID": "18824",
      "srcText": "잡은 물고기들을 한 아름 안고 아기 곰은 집으로 돌아왔어요. \"엄마, 물고기를 이만큼 잡았어요!\" 아기 곰이 자랑스럽게 말했어요.",
      "srcPage": 14,
      "srcSentenceEA": 3,
      "srcWordEA": 18,
      "queAnsPairInfo": [],
      "queAnsPairInfoCount": 0
    },
    {
      "srcTextID": "18805",
      "srcText": "\"얘야, 이제 너도 스스로 물고기를 잡아야지.\" 엄마 곰이 이렇게 말할 때마다 아기 곰은 핑계를 댔어요. \"하지만 엄마, 물고기에게 콱 물리면 어떡해요? 물고기 꼬리지느러미에 철썩 맞으면 어쩌고요?\"",
      "srcPage": 5,
      "srcSentenceEA": 4,
      "srcWordEA": 28,
      "queAnsPairInfo": [],
      "queAnsPairInfoCount": 0
    },
    {
      "srcTextID": "18806",
      "srcText": "어느 날, 풀밭에서 놀다가 잠이 든 아기 곰은 꿈속에서 커다란 물고기 인형과 재미있게 놀았어요. 자기 몸집만 한 아주 큰 물고기 인형이었지요. 잠에서 깬 아기 곰은 꿈에서 본 커다란 물고기 인형이 갖고 싶었어요. 너는 물지도 않고, 꼬리지느러미로 철썩 때리지도 않는구나.",
      "srcPage": 5,
      "srcSentenceEA": 4,
      "srcWordEA": 42,
      "queAnsPairInfo": [],
      "queAnsPairInfoCount": 0
    }
  ]
}